aaxenforo2/__init__.py
aaxenforo2/admin.py
aaxenforo2/app_settings.py
aaxenforo2/apps.py
aaxenforo2/auth_hooks.py
aaxenforo2/manager.py
aaxenforo2/models.py
aaxenforo2/tasks.py
aaxenforo2/tests.py
aaxenforo2/urls.py
aaxenforo2/views.py
aaxenforo2/migrations/0001_initial.py
aaxenforo2/migrations/0002_service_permissions.py
aaxenforo2/migrations/__init__.py
testauth/__init__.py
testauth/celery.py
testauth/settings.py
testauth/urls.py
testauth/wsgi.py
aaxenforo2-1.0.7.dist-info/LICENSE
aaxenforo2-1.0.7.dist-info/METADATA
aaxenforo2-1.0.7.dist-info/WHEEL
aaxenforo2-1.0.7.dist-info/top_level.txt
aaxenforo2-1.0.7.dist-info/RECORD
