Metadata-Version: 2.1
Name: aaxenforo2
Version: 1.0.7
Summary: AA XenForo 2 Service Auth
Home-page: https://github.com/mglinski/aaxenforo2
Author: Matthew Glinski
Author-email: admin@mglinski.com
License: GPLv3
Project-URL: Issue / Bug Reports, https://github.com/mglinski/aaxenforo2/issues
Project-URL: Changelog, https://github.com/mglinski/aaxenforo2/blob/master/CHANGELOG.md
Project-URL: Release Notes, https://github.com/mglinski/aaxenforo2/releases/tag/v1.0.7
Project-URL: Git Repository, https://github.com/mglinski/aaxenforo2
Platform: UNKNOWN
Classifier: Environment :: Web Environment
Classifier: Framework :: Django
Classifier: Framework :: Django :: 3.2
Classifier: Intended Audience :: Developers
Classifier: License :: OSI Approved :: GNU General Public License v3 (GPLv3)
Classifier: Operating System :: OS Independent
Classifier: Programming Language :: Python
Classifier: Programming Language :: Python :: 3
Classifier: Programming Language :: Python :: 3.7
Classifier: Programming Language :: Python :: 3.8
Classifier: Programming Language :: Python :: 3.9
Classifier: Programming Language :: Python :: 3.10
Classifier: Topic :: Internet :: WWW/HTTP
Classifier: Topic :: Internet :: WWW/HTTP :: Dynamic Content
Requires-Python: ~=3.7
Requires-Dist: django (>=3.2)
Requires-Dist: requests (>=2.26.0)
Requires-Dist: allianceauth (>=2.9.0)
Provides-Extra: testing
Requires-Dist: coverage (>=4.3.1) ; extra == 'testing'
Requires-Dist: requests-mock (>=1.2.0) ; extra == 'testing'
Requires-Dist: django-nose ; extra == 'testing'
Requires-Dist: django-webtest ; extra == 'testing'
Requires-Dist: flake8 ; extra == 'testing'
